examples/__init__.py
examples/binary_classification.py
examples/gpt2.py
examples/linear.py
examples/simple_regression.py
nnetflow/__init__.py
nnetflow/device.py
nnetflow/engine.py
nnetflow/layers.py
nnetflow/losses.py
nnetflow/metrics.py
nnetflow/module.py
nnetflow/optim.py
nnetflow/init/__init__.py
nnetflow/init/calculate_gain.py
nnetflow/init/initializers.py
nnetflow-2.0.5.dist-info/licenses/LICENSE
tests/__init__.py
tests/test_conv1&2d.py
tests/test_engine.py
tests/test_linear.py
tests/test_losses.py
tests/test_maxpool.py
tests/test_optimizers.py
tests/test_rnn.py
nnetflow-2.0.5.dist-info/METADATA
nnetflow-2.0.5.dist-info/WHEEL
nnetflow-2.0.5.dist-info/top_level.txt
nnetflow-2.0.5.dist-info/RECORD
