Metadata-Version: 2.4
Name: nnetflow
Version: 2.0.5
Summary: A minimal neural network framework with autodiff and NumPy
Home-page: https://github.com/lewisnjue/nnetflow
Author: Lewis Njue
Author-email: Lewis Njue <lewiskinyuanjue.ke@gmail.com>
License: MIT
Project-URL: Homepage, https://github.com/lewisnjue/nnetflow
Project-URL: Documentation, https://github.com/lewisnjue/nnetflow#readme
Project-URL: Source, https://github.com/lewisnjue/nnetflow
Project-URL: Issues, https://github.com/lewisnjue/nnetflow/issues
Keywords: neural network,autodiff,deep learning,machine learning,numpy,backpropagation,AI,educational
Classifier: Development Status :: 4 - Beta
Classifier: Intended Audience :: Science/Research
Classifier: Intended Audience :: Developers
Classifier: Topic :: Scientific/Engineering :: Artificial Intelligence
Classifier: Topic :: Software Development :: Libraries :: Python Modules
Classifier: Programming Language :: Python :: 3
Classifier: Programming Language :: Python :: 3.8
Classifier: License :: OSI Approved :: MIT License
Classifier: Operating System :: OS Independent
Requires-Python: >=3.8
License-File: LICENSE
Requires-Dist: numpy
Requires-Dist: scipy>=1.9
Provides-Extra: test
Requires-Dist: pytest>=7.0; extra == "test"
Requires-Dist: pytest-cov>=4.0; extra == "test"
Provides-Extra: typecheck
Requires-Dist: mypy>=1.5; extra == "typecheck"
Dynamic: author
Dynamic: home-page
Dynamic: license-file
Dynamic: requires-python
